aurelii/__init__.py
aurelii/aopen.py
aurelii/command_line.py
aurelii-0.1.2.3.data/scripts/aurelii
aurelii-0.1.2.3.dist-info/METADATA
aurelii-0.1.2.3.dist-info/WHEEL
aurelii-0.1.2.3.dist-info/entry_points.txt
aurelii-0.1.2.3.dist-info/top_level.txt
aurelii-0.1.2.3.dist-info/RECORD
