Metadata-Version: 2.1
Name: aurelii
Version: 0.1.2.3
Summary: Aurelii file format python package
Home-page: http://github.com/xonize/opendtk/aurelii
Author: Westsi
Author-email: westsi@protonmail.com
License: GPL-3
Keywords: file format data serialization open source
Classifier: Development Status :: 3 - Alpha
Classifier: License :: OSI Approved :: GNU General Public License v3 (GPLv3)
Classifier: Programming Language :: Python :: 3.10
Classifier: Topic :: Software Development :: Libraries :: Python Modules
Requires-Dist: markdown
